applepassgenerator/__init__.py
applepassgenerator/client.py
applepassgenerator/models.py
applepassgenerator-0.0.1.dist-info/METADATA
applepassgenerator-0.0.1.dist-info/LICENSE
applepassgenerator-0.0.1.dist-info/WHEEL
applepassgenerator-0.0.1.dist-info/RECORD
