Metadata-Version: 2.1
Name: applepassgenerator
Version: 0.0.1
Summary: Python package to create passes compatible with Apple Wallet.
Home-page: https://primedigitalglobal.github.io/applepassgenerator
License: MIT
Keywords: apple pass,apple wallet,passbook,applepassgenerator
Author: Primedigital Global
Author-email: oss@primedigital.tech
Maintainer: Vikalp Jain
Maintainer-email: vikalp@primedigital.tech
Requires-Python: >=3.9,<4.0
Classifier: Development Status :: 4 - Beta
Classifier: Intended Audience :: Developers
Classifier: License :: OSI Approved :: MIT License
Classifier: Natural Language :: English
Classifier: Operating System :: OS Independent
Classifier: Programming Language :: Python :: 3
Classifier: Programming Language :: Python :: 3.9
Classifier: Programming Language :: Python :: 3.10
Classifier: Programming Language :: Python :: 3.11
Classifier: Programming Language :: Python :: 3.9
Requires-Dist: cryptography (>=37.0.2,<38.0.0)
Project-URL: Documentation, https://primedigitalglobal.github.io/applepassgenerator
Project-URL: Repository, https://github.com/PrimedigitalGlobal/applepassgenerator
